neurax/__init__.py
neurax/main.py
neurax-0.1.1.dist-info/LICENCE.md
neurax-0.1.1.dist-info/METADATA
neurax-0.1.1.dist-info/WHEEL
neurax-0.1.1.dist-info/entry_points.txt
neurax-0.1.1.dist-info/top_level.txt
neurax-0.1.1.dist-info/RECORD
