Metadata-Version: 2.1
Name: neurax
Version: 0.1.1
Summary: Easy connections to remote machines
Home-page: https://github.com/LoicGrobol/neurax
Author: Loïc Grobol
Author-email: loic.grobol@gmail.com
License: MIT
Keywords: ssh,sshfs
Platform: UNKNOWN
Classifier: License :: OSI Approved :: MIT License
Classifier: Programming Language :: Python :: 3.8
Classifier: Environment :: Console
Requires-Python: >=3.8
Requires-Dist: click
Requires-Dist: click-pathlib
Requires-Dist: toml
Requires-Dist: xdg
